pymongo_opentracing/__init__.py
pymongo_opentracing/tracing.py
PyMongo_OpenTracing-0.0.3.dist-info/LICENSE
PyMongo_OpenTracing-0.0.3.dist-info/METADATA
PyMongo_OpenTracing-0.0.3.dist-info/WHEEL
PyMongo_OpenTracing-0.0.3.dist-info/top_level.txt
PyMongo_OpenTracing-0.0.3.dist-info/RECORD
