Metadata-Version: 2.1
Name: PyMongo-OpenTracing
Version: 0.0.3
Summary: OpenTracing support for PyMongo
Home-page: http://github.com/signalfx/python-pymongo
Author: SignalFx, Inc.
Author-email: info@signalfx.com
License: Apache Software License v2
Download-URL: http://github.com/signalfx/python-pymongo/tarball/master
Platform: any
Classifier: Development Status :: 4 - Beta
Classifier: Intended Audience :: Developers
Classifier: Natural Language :: English
Classifier: License :: OSI Approved :: Apache Software License
Classifier: Programming Language :: Python
Classifier: Programming Language :: Python :: 2
Classifier: Programming Language :: Python :: 2.7
Classifier: Programming Language :: Python :: 3
Classifier: Programming Language :: Python :: 3.4
Classifier: Programming Language :: Python :: 3.5
Classifier: Programming Language :: Python :: 3.6
Requires-Dist: opentracing (<2.4,>=2.0)
Requires-Dist: pymongo (>=3.1)
Requires-Dist: six
Provides-Extra: integration_tests
Requires-Dist: mock ; extra == 'integration_tests'
Requires-Dist: pytest ; extra == 'integration_tests'
Requires-Dist: docker ; extra == 'integration_tests'
Provides-Extra: unit_tests
Requires-Dist: mock ; extra == 'unit_tests'
Requires-Dist: pytest ; extra == 'unit_tests'
